Metadata-Version: 2.1
Name: waylandmap
Version: 1.1.0
Summary: A keymapper that works under both X11 or Wayland
Home-page: https://github.com/quantumsnowball/waylandmap
Author: Quantum Snowball
Author-email: quantum.snowball@gmail.com
License: UNKNOWN
Keywords: wayland,keymappers,evdev,python-uinput
Platform: UNKNOWN
Requires-Python: >=3.6
License-File: LICENSE
